covidbr/__init__.py
covidbr/api_io/__init__.py
covidbr/api_io/api_io_request.py
covidbr/api_io/browser_slam.py
covidbr/api_io/login_io.py
covidbr/api_io/test_browser_slam.py
covidbr/get_data/__init__.py
covidbr/get_data/work_data.py
covidbr/log/__init__.py
covidbr/log/date.py
covidbr/log/info.py
covidbr/log/logging.py
covidbr/log/puts.py
covidbr/plot_data/__init__.py
covidbr/plot_data/painel.py
covidbr/plot_data/plotting.py
covidbr/social/__init__.py
covidbr/social/insta.py
covidbr/statistical_functions/__init__.py
covidbr/statistical_functions/bases.py
covidbr/statistical_functions/modelling.py
covidbr-0.2.dist-info/LICENSE
covidbr-0.2.dist-info/METADATA
covidbr-0.2.dist-info/WHEEL
covidbr-0.2.dist-info/top_level.txt
covidbr-0.2.dist-info/RECORD
