Metadata-Version: 2.1
Name: covidbr
Version: 0.2
Summary: Library for data mining about covid-19 in brazilian cities
Home-page: https://github.com/gpftc/covid_br
Author: Reinan Br
Author-email: slimchatuba@gmail.com
License: MIT License
Keywords: covid-19 covid api data science
Platform: UNKNOWN
License-File: LICENSE
Requires-Dist: openpyxl
Requires-Dist: numpy
Requires-Dist: matplotlib
Requires-Dist: pillow
Requires-Dist: mechanicalsoup
Requires-Dist: requests
Requires-Dist: pandas
